baka_logger.py
baka_logger-0.0.1.dist-info/METADATA
baka_logger-0.0.1.dist-info/WHEEL
baka_logger-0.0.1.dist-info/licenses/LICENSE
baka_logger-0.0.1.dist-info/RECORD
