Metadata-Version: 2.1
Name: baka_logger
Version: 0.0.1
Summary: A library for turning boring log messages into fun interactions with anime characters.
Project-URL: Homepage, https://github.com/qferbs/baka_logger
Author-email: Quinn Ferbers <gqferbs@gmail.com>
License-File: LICENSE
Classifier: License :: OSI Approved :: MIT License
Classifier: Operating System :: OS Independent
Classifier: Programming Language :: Python :: 3
Requires-Dist: openai
Requires-Dist: python-dotenv
